{
    "timestamp": "2025-04-19 00:56:01",
    "config": {
        "experiment_name": "fl_experiment",
        "experiment_type": "suppression",
        "data_path": "datasets/dataset.parquet",
        "p1_path": null,
        "p2_path": null,
        "feature_columns": [
            "protocol",
            "bidirectional_min_ps",
            "bidirectional_mean_ps",
            "bidirectional_stddev_ps",
            "bidirectional_max_ps",
            "src2dst_stddev_ps",
            "src2dst_max_ps",
            "dst2src_min_ps",
            "dst2src_mean_ps",
            "dst2src_stddev_ps",
            "dst2src_max_ps",
            "bidirectional_stddev_piat_ms",
            "bidirectional_max_piat_ms",
            "bidirectional_rst_packets"
        ],
        "target_column": "application_name",
        "seed": 42,
        "initial_split_ratio": 0.5,
        "test_split_ratio": 0.1667,
        "batch_size": 256,
        "learning_rate": 0.001,
        "local_epochs": 100,
        "federated_rounds": 10,
        "client_epochs": 10,
        "p1_features": null,
        "p2_features": null,
        "max_parallel_suppression_processes": 10,
        "noise_multiplier_p1": null,
        "noise_multiplier_p2": null,
        "noise_multiplier_p1_explicitly_set": false,
        "noise_multiplier_p2_explicitly_set": false,
        "max_grad_norm": 1.0,
        "max_epsilon": 10.0,
        "max_parallel_dp_processes": 2,
        "results_dir": "results",
        "logs_dir": "logs",
        "save_models": false,
        "checkpoint_interval": 1
    },
    "results": {
        "experiment_id": "178",
        "p1_features": [
            "protocol",
            "bidirectional_min_ps"
        ],
        "p2_features": [
            "protocol",
            "bidirectional_min_ps",
            "bidirectional_mean_ps",
            "bidirectional_stddev_ps",
            "bidirectional_max_ps"
        ],
        "rounds": [
            {
                "round": 1,
                "time": 216.64108109474182,
                "client_training": {
                    "P1": {
                        "loss": [
                            0.2657485140125597,
                            0.08125899739812165,
                            0.0732515471829702,
                            0.07141426156577146,
                            0.0700905636747715,
                            0.0680526304682166,
                            0.0663177624224401,
                            0.06539485505258562,
                            0.06497692771870177,
                            0.06477732864417868
                        ],
                        "accuracy": [
                            0.9303056628104986,
                            0.9812457070885455,
                            0.9825781065649043,
                            0.982833614642717,
                            0.9828328631483705,
                            0.9827637256684918,
                            0.9827599681967593,
                            0.9829794045459396,
                            0.9835452797888602,
                            0.9840247331819323
                        ],
                        "val_loss": [
                            0.0892976532073041,
                            0.07605670454318995,
                            0.07198112987784552,
                            0.07109183970717861,
                            0.06907392225636438,
                            0.06732809624443357,
                            0.06600651058232267,
                            0.06556699635240472,
                            0.06524700186073723,
                            0.06458282325056297
                        ],
                        "val_accuracy": [
                            0.9811946611770804,
                            0.9817806845203436,
                            0.9828250081705178,
                            0.9828287647304105,
                            0.9828362778501959,
                            0.982573318657706,
                            0.9828400344100886,
                            0.981829519798949,
                            0.9845830782003073,
                            0.9843013362083538
                        ]
                    },
                    "P2": {
                        "loss": [
                            0.3996821385154887,
                            0.1869246550967802,
                            0.16595134155403476,
                            0.1507265342580616,
                            0.13619774733222062,
                            0.1260588489416306,
                            0.12061467717084774,
                            0.11756220453778649,
                            0.11584898323027498,
                            0.11448267342248686
                        ],
                        "accuracy": [
                            0.8241292141286779,
                            0.9280865308748841,
                            0.935903112384425,
                            0.943273863784347,
                            0.9499145875305455,
                            0.9523107328619689,
                            0.9532054572056717,
                            0.954760500371525,
                            0.9555962403192818,
                            0.9562029369632995
                        ],
                        "val_loss": [
                            0.20861536146830315,
                            0.17730469984773545,
                            0.15830170424604317,
                            0.14517113236643192,
                            0.13053468792977949,
                            0.12255754551117741,
                            0.11957814008449086,
                            0.117504541532389,
                            0.11597537510156512,
                            0.11381176722444614
                        ],
                        "val_accuracy": [
                            0.9176983254770266,
                            0.9312729514568312,
                            0.9425998184944228,
                            0.9445144342884714,
                            0.9519776066536728,
                            0.952613259097297,
                            0.953202960761864,
                            0.9546197764494598,
                            0.9537467116473737,
                            0.9568637061600849
                        ]
                    }
                },
                "global_evaluation": {
                    "P1": {
                        "loss": 3.284902091481306,
                        "accuracy": 0.2538608044297354
                    },
                    "P2": {
                        "loss": 5.170260479160553,
                        "accuracy": 0.2512818352741155
                    }
                }
            },
            {
                "round": 2,
                "time": 216.3549349308014,
                "client_training": {
                    "P1": {
                        "loss": [
                            0.1691266684437234,
                            0.07755395576509755,
                            0.07111191492060363,
                            0.06801872265648687,
                            0.0660903815908211,
                            0.06473336034487746,
                            0.06445409208232902,
                            0.06427909778712174,
                            0.0640503294740899,
                            0.06395172940520134
                        ],
                        "accuracy": [
                            0.9701679289266707,
                            0.9812637429528618,
                            0.9824683883903141,
                            0.9838090543044845,
                            0.9843771840304445,
                            0.9843689175926329,
                            0.9844290371403536,
                            0.9843959713891073,
                            0.9844771327785301,
                            0.9844433155329373
                        ],
                        "val_loss": [
                            0.08191488102745349,
                            0.07442684129533922,
                            0.0693910206918398,
                            0.0676247408761461,
                            0.0656589575065377,
                            0.06506273916059682,
                            0.06506128509250124,
                            0.06427722177385901,
                            0.06421886302994284,
                            0.06523618558650922
                        ],
                        "val_accuracy": [
                            0.9812284702161149,
                            0.9812209570963295,
                            0.9828362778501959,
                            0.9835387545501332,
                            0.984560538840951,
                            0.9850413785072182,
                            0.9828212516106251,
                            0.9842825534088903,
                            0.984560538840951,
                            0.9857100461681211
                        ]
                    },
                    "P2": {
                        "loss": [
                            0.30405491099357296,
                            0.169330134965618,
                            0.14672648127593788,
                            0.12428394435377894,
                            0.11727915396359058,
                            0.11409883838124867,
                            0.11164703824692009,
                            0.11023562216510252,
                            0.10931091917735203,
                            0.1084994301670315
                        ],
                        "accuracy": [
                            0.884595114253541,
                            0.9344997433795761,
                            0.9423737772228308,
                            0.9543951035291054,
                            0.9556919942088048,
                            0.9565729299924163,
                            0.9576890373286963,
                            0.9581946178653777,
                            0.9584573665382288,
                            0.9586182330726274
                        ],
                        "val_loss": [
                            0.1863217051017661,
                            0.15890666003558848,
                            0.13308004108931096,
                            0.12051491558746248,
                            0.11631698462620416,
                            0.11313665925524548,
                            0.11179784345078896,
                            0.11147357547591959,
                            0.10884981992851962,
                            0.10879149415790554
                        ],
                        "val_accuracy": [
                            0.9288030970825084,
                            0.9404516195735002,
                            0.9529464022454615,
                            0.9559485198105296,
                            0.9561706152426392,
                            0.958089060268276,
                            0.9578018678991687,
                            0.9585600557536119,
                            0.9590616850916527,
                            0.9579397202363402
                        ]
                    }
                },
                "global_evaluation": {
                    "P1": {
                        "loss": 5.362237601250997,
                        "accuracy": 0.18772281095863652
                    },
                    "P2": {
                        "loss": 4.873786405071649,
                        "accuracy": 0.32008163921745825
                    }
                }
            },
            {
                "round": 3,
                "time": 216.7628619670868,
                "client_training": {
                    "P1": {
                        "loss": [
                            0.13754760732369242,
                            0.0695927707788584,
                            0.06608391898774474,
                            0.06474017698003026,
                            0.06391690352536634,
                            0.06350554249681474,
                            0.06305902235904104,
                            0.06276120305970595,
                            0.06249900687029156,
                            0.06247536720800909
                        ],
                        "accuracy": [
                            0.9731987056261375,
                            0.9821369793835041,
                            0.9831507452569435,
                            0.9840931191674646,
                            0.9845860994587737,
                            0.9847574401697776,
                            0.9848957151295351,
                            0.9849145024881978,
                            0.9850384990553716,
                            0.9851068850409038
                        ],
                        "val_loss": [
                            0.07324021598706539,
                            0.06729759620302578,
                            0.06552673308042373,
                            0.06556946323486551,
                            0.06496104523993237,
                            0.06374077896499993,
                            0.0636201294084387,
                            0.06411527301692758,
                            0.0630915707623147,
                            0.06299833352171089
                        ],
                        "val_accuracy": [
                            0.9817468754813092,
                            0.9825582924181352,
                            0.9825507792983498,
                            0.9825395096186716,
                            0.9837303391046616,
                            0.9845530257211655,
                            0.9850038129082911,
                            0.9852780417804591,
                            0.9845492691612728,
                            0.9845492691612728
                        ]
                    },
                    "P2": {
                        "loss": [
                            0.22522594505098872,
                            0.13920283185625068,
                            0.12516562988963612,
                            0.11984201513199011,
                            0.11753775778883266,
                            0.11624952262051318,
                            0.11539379000704508,
                            0.11484432995076689,
                            0.1141357364284146,
                            0.11354753299942047
                        ],
                        "accuracy": [
                            0.9239262158828891,
                            0.9492083068414239,
                            0.9535394467723279,
                            0.9550232490443762,
                            0.9555855158836551,
                            0.9561140773538221,
                            0.9564411726404326,
                            0.956500923067495,
                            0.9568487011942425,
                            0.9570662540312388
                        ],
                        "val_loss": [
                            0.15102681783569072,
                            0.13090719794694933,
                            0.12280285262134503,
                            0.11892991006266858,
                            0.11831574299287924,
                            0.1167487167636916,
                            0.1151605103055513,
                            0.11682460800767484,
                            0.11317600008840183,
                            0.11504069783768078
                        ],
                        "val_accuracy": [
                            0.9448858697525168,
                            0.9523643590440706,
                            0.9545048995018169,
                            0.9555541089569556,
                            0.9540453917112452,
                            0.9555196458726627,
                            0.9563237845061632,
                            0.9553588181459627,
                            0.9568369015389682,
                            0.9564960999276275
                        ]
                    }
                },
                "global_evaluation": {
                    "P1": {
                        "loss": 1.566079515388838,
                        "accuracy": 0.7469994477856958
                    },
                    "P2": {
                        "loss": 2.514219646194595,
                        "accuracy": 0.4253816786585436
                    }
                }
            },
            {
                "round": 4,
                "time": 215.90047883987427,
                "client_training": {
                    "P1": {
                        "loss": [
                            0.08557097997743027,
                            0.06460851241828056,
                            0.06379714302291217,
                            0.06318563118501684,
                            0.06255790049896723,
                            0.06224411923393109,
                            0.06195932695066482,
                            0.061548812757577974,
                            0.06134047540098786,
                            0.061135030114112865
                        ],
                        "accuracy": [
                            0.9817860315236848,
                            0.9844027348382258,
                            0.9847559371810846,
                            0.984789002932331,
                            0.9848754247821794,
                            0.984894212140842,
                            0.9849265263977419,
                            0.9849633496207209,
                            0.9849663555981069,
                            0.9849851429567695
                        ],
                        "val_loss": [
                            0.06717515369222266,
                            0.06417694844987848,
                            0.06387608223648236,
                            0.06349769812201063,
                            0.06353803870868671,
                            0.06240362677865897,
                            0.06260145092692265,
                            0.06463815481333321,
                            0.061562845184231656,
                            0.061564410912208614
                        ],
                        "val_accuracy": [
                            0.9845267298019166,
                            0.984534242921702,
                            0.9845417560414874,
                            0.9842750402891048,
                            0.9837190694249833,
                            0.9842825534088903,
                            0.9850000563483984,
                            0.9850188391478619,
                            0.9850188391478619,
                            0.9850338653874328
                        ]
                    },
                    "P2": {
                        "loss": [
                            0.14155460434979053,
                            0.11899785549040988,
                            0.11622985215040343,
                            0.11512604904024998,
                            0.11434378041417324,
                            0.11390097345778294,
                            0.11326557121023229,
                            0.11300934946816085,
                            0.11256312777148578,
                            0.11219217846561437
                        ],
                        "accuracy": [
                            0.9497567851206116,
                            0.9554499283760907,
                            0.9560865002336395,
                            0.9564419386715488,
                            0.9566931968776572,
                            0.9568908329056326,
                            0.9570938311514213,
                            0.9572531656235876,
                            0.957475314647281,
                            0.957733467133435
                        ],
                        "val_loss": [
                            0.12368702229080619,
                            0.11899065208262669,
                            0.11589186540213679,
                            0.11509678007727978,
                            0.11358488711934095,
                            0.11379565882001458,
                            0.11302885026947858,
                            0.11355867699372424,
                            0.11594455916185045,
                            0.11165623000484727
                        ],
                        "val_accuracy": [
                            0.9523069205702491,
                            0.9540185870901287,
                            0.9565650260962133,
                            0.9554200858513722,
                            0.957181532381897,
                            0.9570475092763135,
                            0.9573117262558922,
                            0.9573653354981256,
                            0.9561055183056416,
                            0.9573232139506566
                        ]
                    }
                },
                "global_evaluation": {
                    "P1": {
                        "loss": 3.457476591419137,
                        "accuracy": 0.8406767818302711
                    },
                    "P2": {
                        "loss": 2.627721760497924,
                        "accuracy": 0.4495939099900823
                    }
                }
            },
            {
                "round": 5,
                "time": 215.46884608268738,
                "client_training": {
                    "P1": {
                        "loss": [
                            0.11366123912207468,
                            0.06552093523192257,
                            0.06493800611334959,
                            0.06436079739232027,
                            0.06408021564611102,
                            0.06372955182260406,
                            0.0635666543774011,
                            0.0634845626628666,
                            0.0632839264028686,
                            0.06311803443658548
                        ],
                        "accuracy": [
                            0.9810458095923744,
                            0.9835715820909879,
                            0.9841006341109296,
                            0.9843501302339702,
                            0.9843268339092285,
                            0.9843478757509307,
                            0.9843072950562193,
                            0.9842111037798663,
                            0.9842584479236963,
                            0.984235903093301
                        ],
                        "val_loss": [
                            0.06623267134075908,
                            0.06529892127654852,
                            0.06490803184166688,
                            0.06457003998369149,
                            0.06573387227331162,
                            0.06464061311679895,
                            0.06478391374050023,
                            0.06375485814105245,
                            0.06332998394266244,
                            0.06306619497916177
                        ],
                        "val_accuracy": [
                            0.9828550606496594,
                            0.9828400344100886,
                            0.9825921014571696,
                            0.9845943478799855,
                            0.9850225957077546,
                            0.9850526481868964,
                            0.9845718085206292,
                            0.9845680519607365,
                            0.9845718085206292,
                            0.9845755650805219
                        ]
                    },
                    "P2": {
                        "loss": [
                            0.1346494600692872,
                            0.11423832614019014,
                            0.1129401430430673,
                            0.11204676844566192,
                            0.11150628723718999,
                            0.11106370122687322,
                            0.11072822472185076,
                            0.11032142420969433,
                            0.11005146388351247,
                            0.10987609356085186
                        ],
                        "accuracy": [
                            0.9521368437985951,
                            0.9572240564411726,
                            0.9576974636709743,
                            0.9579609783749415,
                            0.9581118865048298,
                            0.9581900216786806,
                            0.9584106386401415,
                            0.9583156507817348,
                            0.9584366836980918,
                            0.9583991481733988
                        ],
                        "val_loss": [
                            0.11537133165024838,
                            0.11375490251046463,
                            0.11367004233699203,
                            0.1190998278548925,
                            0.11752440911955907,
                            0.112409914512166,
                            0.11136351344549576,
                            0.11233007190822977,
                            0.11149077716869767,
                            0.11074137230141812
                        ],
                        "val_accuracy": [
                            0.9569134861707301,
                            0.9572964093295399,
                            0.9578248432886972,
                            0.9582422295317998,
                            0.9554698658620174,
                            0.9568483892337325,
                            0.9571585569923683,
                            0.9574763832141804,
                            0.9586289819221977,
                            0.9581618156684498
                        ]
                    }
                },
                "global_evaluation": {
                    "P1": {
                        "loss": 5.471452819297543,
                        "accuracy": 0.3380528247452113
                    },
                    "P2": {
                        "loss": 4.569415664070664,
                        "accuracy": 0.475027666198224
                    }
                }
            },
            {
                "round": 6,
                "time": 216.89622020721436,
                "client_training": {
                    "P1": {
                        "loss": [
                            0.1325638186994772,
                            0.06625154948206823,
                            0.06366535353649426,
                            0.06214405951366022,
                            0.0612527497228551,
                            0.0606509343299602,
                            0.06029744338837079,
                            0.05989732536285996,
                            0.05980481855824717,
                            0.05954646461661793
                        ],
                        "accuracy": [
                            0.9755621553459053,
                            0.9844906596767673,
                            0.98474616775458,
                            0.9849122480051583,
                            0.9849919064058881,
                            0.9851376963091106,
                            0.9851963128681382,
                            0.9852301301137312,
                            0.9852722137971356,
                            0.9853353393222423
                        ],
                        "val_loss": [
                            0.07039625327076464,
                            0.06598271895433369,
                            0.06305002958893122,
                            0.062114410225880885,
                            0.06259083847777304,
                            0.06156051615874122,
                            0.061514820733971014,
                            0.06022218662509159,
                            0.05974625962937588,
                            0.06035732822849678
                        ],
                        "val_accuracy": [
                            0.9828287647304105,
                            0.9829602443266554,
                            0.9845793216404146,
                            0.9850188391478619,
                            0.984338901807281,
                            0.9850413785072182,
                            0.985698776488443,
                            0.9842938230885684,
                            0.9851089965852871,
                            0.9847483668355866
                        ]
                    },
                    "P2": {
                        "loss": [
                            0.13625997184358324,
                            0.11158088561507787,
                            0.11082321355408441,
                            0.11040607181678923,
                            0.1101523044077511,
                            0.1097522337189542,
                            0.10970703608283297,
                            0.10940282269425954,
                            0.109207839587742,
                            0.10920546464868865
                        ],
                        "accuracy": [
                            0.952815547367534,
                            0.9580827773224149,
                            0.9584412798847889,
                            0.9584826455650629,
                            0.9586151689481627,
                            0.9586243613215569,
                            0.9586534705039719,
                            0.9587170510866151,
                            0.9588235294117647,
                            0.9588105068827896
                        ],
                        "val_loss": [
                            0.11316031543227889,
                            0.11097324580350486,
                            0.11148896553022167,
                            0.11088940275549344,
                            0.10973191283482137,
                            0.10930323859239419,
                            0.10990311933369971,
                            0.11005472383641421,
                            0.10871408695059423,
                            0.11001451635593613
                        ],
                        "val_accuracy": [
                            0.9573193847190684,
                            0.9584681541954976,
                            0.9586251526906095,
                            0.9580239633312783,
                            0.9584528372691452,
                            0.958797468112074,
                            0.9586634450064906,
                            0.9588242727331906,
                            0.9583685941742071,
                            0.9589927589230669
                        ]
                    }
                },
                "global_evaluation": {
                    "P1": {
                        "loss": 8.729905006296658,
                        "accuracy": 0.35160649283811857
                    },
                    "P2": {
                        "loss": 4.8735541609886175,
                        "accuracy": 0.5658532102363019
                    }
                }
            },
            {
                "round": 7,
                "time": 215.90872597694397,
                "client_training": {
                    "P1": {
                        "loss": [
                            0.14510247428199816,
                            0.06260153812604902,
                            0.060976647040663495,
                            0.06026484666601111,
                            0.059949409917326696,
                            0.05976807629555804,
                            0.05961677929413241,
                            0.05955927090040542,
                            0.05955329629780783,
                            0.05944333248276874
                        ],
                        "accuracy": [
                            0.9746671255792143,
                            0.9844966716315393,
                            0.9849114965108118,
                            0.9851775255094756,
                            0.9852662018423636,
                            0.9853436057600539,
                            0.9853684050734887,
                            0.9854382940477139,
                            0.9854706083046137,
                            0.9854578329007231
                        ],
                        "val_loss": [
                            0.06581655894261282,
                            0.062448852193070704,
                            0.06096731625333132,
                            0.060061138863333155,
                            0.060842160540152075,
                            0.06119826095254174,
                            0.059839485075309895,
                            0.0594003496851966,
                            0.05976893724509916,
                            0.059843233495907706
                        ],
                        "val_accuracy": [
                            0.9829489746469773,
                            0.9847220709163377,
                            0.9854170344964895,
                            0.9847859324345137,
                            0.9847258274762304,
                            0.9854358172959531,
                            0.9847258274762304,
                            0.984639426598698,
                            0.9856837502488721,
                            0.9850000563483984
                        ]
                    },
                    "P2": {
                        "loss": [
                            0.16449210158673264,
                            0.112523653225262,
                            0.11108824325393823,
                            0.11049947399714903,
                            0.10984228500469997,
                            0.1094381936749968,
                            0.10903800658394654,
                            0.10880676430326083,
                            0.10849762313538144,
                            0.10838707308965222
                        ],
                        "accuracy": [
                            0.9493745355936358,
                            0.9576177964348912,
                            0.9580191967397715,
                            0.9582061083321205,
                            0.9582612625724857,
                            0.9585025623740836,
                            0.9585738032678888,
                            0.958570739143424,
                            0.9587362018645197,
                            0.9587101568065695
                        ],
                        "val_loss": [
                            0.11458561641339324,
                            0.1117957941689795,
                            0.1116175298171454,
                            0.11093922728203755,
                            0.11407251638640739,
                            0.10944565359346729,
                            0.10855587028605392,
                            0.11099359578456389,
                            0.10863191409283508,
                            0.10870315273386508
                        ],
                        "val_accuracy": [
                            0.9572351416241303,
                            0.9575759432354709,
                            0.9579435494679283,
                            0.958801297343662,
                            0.9538309547423118,
                            0.9583341310899142,
                            0.9588204435016026,
                            0.9580048171733379,
                            0.9591880497340599,
                            0.958169474131626
                        ]
                    }
                },
                "global_evaluation": {
                    "P1": {
                        "loss": 12.777072272202792,
                        "accuracy": 0.2919861307808761
                    },
                    "P2": {
                        "loss": 2.9855392883591096,
                        "accuracy": 0.5930024621959111
                    }
                }
            },
            {
                "round": 8,
                "time": 216.2875270843506,
                "client_training": {
                    "P1": {
                        "loss": [
                            0.18166909881029886,
                            0.061404898676365297,
                            0.05982471979033838,
                            0.05967800619822817,
                            0.05956867912114097,
                            0.05947350916905725,
                            0.05935117599481604,
                            0.059304170578401545,
                            0.05926721433807259,
                            0.05932078432955017
                        ],
                        "accuracy": [
                            0.9756621040939909,
                            0.9852729652914821,
                            0.9853954588699629,
                            0.985442803013793,
                            0.9854886441689299,
                            0.9854886441689299,
                            0.9855149464710578,
                            0.9855667995809667,
                            0.9855269703806018,
                            0.9854826322141579
                        ],
                        "val_loss": [
                            0.06602271676673577,
                            0.06017510821445806,
                            0.06039239221227532,
                            0.05960566246208698,
                            0.06058613290401209,
                            0.059570764616899176,
                            0.060162764180039685,
                            0.05991252793181417,
                            0.06076078204667268,
                            0.0603283520725302
                        ],
                        "val_accuracy": [
                            0.9857438552071555,
                            0.9850075694681838,
                            0.9851052400253943,
                            0.9851089965852871,
                            0.9856950199285502,
                            0.9850188391478619,
                            0.9857025330483357,
                            0.9856912633686575,
                            0.9849324382703296,
                            0.9849700038692567
                        ]
                    },
                    "P2": {
                        "loss": [
                            0.13432609009139856,
                            0.11017070901141579,
                            0.10932352195438366,
                            0.10892962428711614,
                            0.1084478187160423,
                            0.10820637791085248,
                            0.10798971051203399,
                            0.10779754068022797,
                            0.10767432073142462,
                            0.10745213581722474
                        ],
                        "accuracy": [
                            0.9540549857135197,
                            0.9580467738599542,
                            0.9582344514834192,
                            0.9583064584083405,
                            0.9584075745156768,
                            0.9584228951380005,
                            0.9584282573558138,
                            0.9584941360318057,
                            0.958483411596179,
                            0.9585232452142206
                        ],
                        "val_loss": [
                            0.11067679649308908,
                            0.11112542355919536,
                            0.10955062907295506,
                            0.1100514700673649,
                            0.10716139846408614,
                            0.1089399763314139,
                            0.10992886206701424,
                            0.10928309032726935,
                            0.11177986151458866,
                            0.1077619932001601
                        ],
                        "val_accuracy": [
                            0.9576372109408805,
                            0.9582115956790951,
                            0.9581962787527427,
                            0.9581924495211546,
                            0.9581886202895665,
                            0.9578248432886972,
                            0.9579818417838093,
                            0.957104947750135,
                            0.9580316217944546,
                            0.9579397202363402
                        ]
                    }
                },
                "global_evaluation": {
                    "P1": {
                        "loss": 15.632957047013324,
                        "accuracy": 0.27767739414953363
                    },
                    "P2": {
                        "loss": 2.5074008657519906,
                        "accuracy": 0.5930484129749684
                    }
                }
            },
            {
                "round": 9,
                "time": 216.1338770389557,
                "client_training": {
                    "P1": {
                        "loss": [
                            0.211434090209909,
                            0.0612457895257372,
                            0.06051554341083582,
                            0.05982980111259871,
                            0.05976642075211731,
                            0.0595162634048946,
                            0.05942807086540363,
                            0.05938866853988836,
                            0.059356108833143115,
                            0.05924981829178985
                        ],
                        "accuracy": [
                            0.9742763485190301,
                            0.9850850917048551,
                            0.9851331873430316,
                            0.9853030250653424,
                            0.9854195066890512,
                            0.9854653478441882,
                            0.98550367405586,
                            0.9855472607279575,
                            0.9855622906148878,
                            0.9855705570526992
                        ],
                        "val_loss": [
                            0.06241890403462422,
                            0.06160870336807287,
                            0.06095411720344554,
                            0.06052510816728434,
                            0.0604509918719792,
                            0.06187121621509898,
                            0.059649655761316936,
                            0.06003935707528446,
                            0.06008641351300125,
                            0.060003768515981444
                        ],
                        "val_accuracy": [
                            0.984966247309364,
                            0.9847032881168741,
                            0.9847333405960158,
                            0.9850075694681838,
                            0.9847483668355866,
                            0.9837566350239105,
                            0.9854320607360604,
                            0.9856875068087648,
                            0.9856950199285502,
                            0.9856950199285502
                        ]
                    },
                    "P2": {
                        "loss": [
                            0.12463424447700883,
                            0.1090818968249929,
                            0.10881973532883554,
                            0.10851231382021606,
                            0.10834206182023079,
                            0.10819582171052634,
                            0.10811819058997833,
                            0.10780151982351834,
                            0.10775039825264086,
                            0.10768003384145478
                        ],
                        "accuracy": [
                            0.9551343235562229,
                            0.9584305554491623,
                            0.9583279072795937,
                            0.958478815409482,
                            0.9583815294577266,
                            0.9584121707023739,
                            0.958425193231349,
                            0.9585186490275235,
                            0.9586243613215569,
                            0.9585699731123078
                        ],
                        "val_loss": [
                            0.10936067019111365,
                            0.10867154328193941,
                            0.11101210384848767,
                            0.10849469126597375,
                            0.10954239439556018,
                            0.10755349060513461,
                            0.10742243245363339,
                            0.10879283319010802,
                            0.1111922983323267,
                            0.10757174668332377
                        ],
                        "val_accuracy": [
                            0.9579550371626926,
                            0.958881711207012,
                            0.9585906896063167,
                            0.9583111557003856,
                            0.9589238327544811,
                            0.9587783219541335,
                            0.9593450482291719,
                            0.9582958387740332,
                            0.9582805218476809,
                            0.9580584264155712
                        ]
                    }
                },
                "global_evaluation": {
                    "P1": {
                        "loss": 17.368897377988123,
                        "accuracy": 0.2914752386354672
                    },
                    "P2": {
                        "loss": 3.622042220015119,
                        "accuracy": 0.5645551007279369
                    }
                }
            },
            {
                "round": 10,
                "time": 216.39280223846436,
                "client_training": {
                    "P1": {
                        "loss": [
                            0.22172609149299582,
                            0.061168760054657136,
                            0.06047011400814568,
                            0.05994212166719475,
                            0.05988432644839348,
                            0.0597534043729502,
                            0.05959731895371267,
                            0.05954217978359685,
                            0.05939529583205161,
                            0.05940101485220185
                        ],
                        "accuracy": [
                            0.9743274501345927,
                            0.9851474657356153,
                            0.9852353905741567,
                            0.9853278243787772,
                            0.9853992163416955,
                            0.9853736655339141,
                            0.9854157492173187,
                            0.9854600873837626,
                            0.9854736142819998,
                            0.9855217099201763
                        ],
                        "val_loss": [
                            0.06230027183078843,
                            0.06128807105798101,
                            0.061435914538541345,
                            0.06041101229925481,
                            0.06250849119705465,
                            0.060128390603271964,
                            0.059765692139935524,
                            0.06113371807067994,
                            0.059807729151359554,
                            0.05963243762433414
                        ],
                        "val_accuracy": [
                            0.9847220709163377,
                            0.9847408537158012,
                            0.9847295840361231,
                            0.9856687240093013,
                            0.9847408537158012,
                            0.9854470869756312,
                            0.9854320607360604,
                            0.9854207910563823,
                            0.9847596365152648,
                            0.9854395738558458
                        ]
                    },
                    "P2": {
                        "loss": [
                            0.13506272438718878,
                            0.10849923565923845,
                            0.10806132365168034,
                            0.1078865712705107,
                            0.107613201129316,
                            0.10738531831541002,
                            0.10724202211376853,
                            0.10713322322793141,
                            0.1070456647005883,
                            0.10690765318747138
                        ],
                        "accuracy": [
                            0.9552821675616463,
                            0.9587430961445654,
                            0.9587882919804203,
                            0.958562312801146,
                            0.9587201152110799,
                            0.9585799315168182,
                            0.9587859938870716,
                            0.9587607148602376,
                            0.9587093907754533,
                            0.9588618309675739
                        ],
                        "val_loss": [
                            0.1091079961420312,
                            0.10956152251284137,
                            0.10700527829077129,
                            0.1069562168863693,
                            0.10677728414964842,
                            0.10672846318232293,
                            0.10837047134712258,
                            0.10654579320437249,
                            0.10608938194361454,
                            0.10857889258429232
                        ],
                        "val_accuracy": [
                            0.9583188141635618,
                            0.9587170542487239,
                            0.9590961481759456,
                            0.9593641943871123,
                            0.9595173636506362,
                            0.9590119050810074,
                            0.9587170542487239,
                            0.9593565359239361,
                            0.958364764942619,
                            0.9581350110473331
                        ]
                    }
                },
                "global_evaluation": {
                    "P1": {
                        "loss": 16.681491570570504,
                        "accuracy": 0.27715147576455385
                    },
                    "P2": {
                        "loss": 5.774632341090301,
                        "accuracy": 0.5542429800611911
                    }
                }
            }
        ],
        "final_evaluation": {
            "P1": {
                "loss": 16.681491570570504,
                "accuracy": 0.27715147576455385
            },
            "P2": {
                "loss": 5.774632341090301,
                "accuracy": 0.5542429800611911
            }
        }
    }
}