{
    "timestamp": "2025-03-05 03:24:01",
    "config": {
        "experiment_name": "fl_experiment",
        "experiment_type": "suppression",
        "data_path": "datasets/dataset.parquet",
        "p1_path": null,
        "p2_path": null,
        "feature_columns": [
            "protocol",
            "bidirectional_min_ps",
            "bidirectional_mean_ps",
            "bidirectional_stddev_ps",
            "bidirectional_max_ps",
            "src2dst_stddev_ps",
            "src2dst_max_ps",
            "dst2src_min_ps",
            "dst2src_mean_ps",
            "dst2src_stddev_ps",
            "dst2src_max_ps",
            "bidirectional_stddev_piat_ms",
            "bidirectional_max_piat_ms",
            "bidirectional_rst_packets"
        ],
        "target_column": "application_name",
        "seed": 42,
        "initial_split_ratio": 0.5,
        "test_split_ratio": 0.1667,
        "batch_size": 256,
        "learning_rate": 0.001,
        "local_epochs": 100,
        "federated_rounds": 10,
        "client_epochs": 10,
        "p1_features": null,
        "p2_features": null,
        "max_parallel_suppression_processes": 10,
        "noise_multiplier_p1": null,
        "noise_multiplier_p2": null,
        "noise_multiplier_p1_explicitly_set": false,
        "noise_multiplier_p2_explicitly_set": false,
        "max_grad_norm": 1.0,
        "max_epsilon": 10.0,
        "max_parallel_dp_processes": 2,
        "results_dir": "results",
        "logs_dir": "logs",
        "save_models": false,
        "checkpoint_interval": 1
    },
    "results": {
        "experiment_id": "171",
        "p1_features": [
            "protocol",
            "bidirectional_min_ps"
        ],
        "p2_features": [
            "protocol",
            "bidirectional_min_ps",
            "bidirectional_mean_ps",
            "bidirectional_stddev_ps",
            "bidirectional_max_ps",
            "src2dst_stddev_ps",
            "src2dst_max_ps",
            "dst2src_min_ps",
            "dst2src_mean_ps",
            "dst2src_stddev_ps",
            "dst2src_max_ps",
            "bidirectional_stddev_piat_ms"
        ],
        "rounds": [
            {
                "round": 1,
                "time": 237.18489599227905,
                "client_training": {
                    "P1": {
                        "loss": [
                            0.9602311738660023,
                            0.8179118903923547,
                            0.8115327821141721,
                            0.8086035163532926,
                            0.805961743180498,
                            0.8008634385631128,
                            0.7960358935954849,
                            0.7923813557331346,
                            0.7894510527916712,
                            0.7870976345191082
                        ],
                        "accuracy": [
                            0.6416813853129154,
                            0.6795424473618723,
                            0.6798580636938036,
                            0.6811440485078024,
                            0.6836484944494012,
                            0.6908849092906523,
                            0.6961009243916799,
                            0.6982396802563776,
                            0.7001341369410707,
                            0.7010733990058086
                        ],
                        "val_loss": [
                            0.8283745451010583,
                            0.8160459304100034,
                            0.8113640956714999,
                            0.8087655570862632,
                            0.8061760111963668,
                            0.7998991288527998,
                            0.7939134074200089,
                            0.7929153654041183,
                            0.7877967296008805,
                            0.7852569458933818
                        ],
                        "val_accuracy": [
                            0.6869062292595051,
                            0.6799393192376979,
                            0.6825182516355361,
                            0.68,
                            0.6825334218261117,
                            0.6958111311273348,
                            0.7016440694036219,
                            0.6933004645870864,
                            0.701230681710439,
                            0.7019019626434057
                        ]
                    },
                    "P2": {
                        "loss": [
                            0.36117795426517335,
                            0.20464804111528165,
                            0.17795326995329164,
                            0.1469445118295568,
                            0.12453774723974122,
                            0.1156019412996648,
                            0.11082191399361359,
                            0.10741555146930022,
                            0.10433153056628337,
                            0.10191540560577092
                        ],
                        "accuracy": [
                            0.8738156800621522,
                            0.9269727538131916,
                            0.9379244887925855,
                            0.9540580976832548,
                            0.9620554817094266,
                            0.9642048592776028,
                            0.9656274088506103,
                            0.9668959437231802,
                            0.9681326134853148,
                            0.9689026869875028
                        ],
                        "val_loss": [
                            0.219157035022796,
                            0.18976490237232044,
                            0.16478401024335707,
                            0.13244329409654915,
                            0.1179688141983053,
                            0.11242070052619114,
                            0.11003536808736021,
                            0.10419143634214552,
                            0.10383619386807678,
                            0.10084580252642336
                        ],
                        "val_accuracy": [
                            0.9229088840428558,
                            0.93274675263108,
                            0.9432824499857779,
                            0.9601668720963307,
                            0.9637659998103726,
                            0.9637584147150848,
                            0.9672437659998103,
                            0.9680022755285863,
                            0.9679378022186403,
                            0.9695382573243576
                        ]
                    }
                },
                "global_evaluation": {
                    "P1": {
                        "loss": 2.1747059599130516,
                        "accuracy": 0.4382554280838153
                    },
                    "P2": {
                        "loss": 1.9556152120454398,
                        "accuracy": 0.438706741253437
                    }
                }
            },
            {
                "round": 2,
                "time": 244.3102560043335,
                "client_training": {
                    "P1": {
                        "loss": [
                            0.8443883198242422,
                            0.8067759626862756,
                            0.7990050928874156,
                            0.7958021125389892,
                            0.7936594089776706,
                            0.7920322140700391,
                            0.7906837394754174,
                            0.7892697701403832,
                            0.7881850981562278,
                            0.787516144224224
                        ],
                        "accuracy": [
                            0.6899661319397659,
                            0.6972533792190924,
                            0.7002153171033704,
                            0.7014072239722743,
                            0.7018798897770656,
                            0.7020832195293675,
                            0.7021871604848352,
                            0.7021135672535916,
                            0.7022827558161413,
                            0.7023525555818569
                        ],
                        "val_loss": [
                            0.8121487428459995,
                            0.8026214446514672,
                            0.797482294884408,
                            0.7965696415160181,
                            0.7930883221663807,
                            0.7909229687956303,
                            0.7905466629767787,
                            0.7910552201859248,
                            0.7883109853065804,
                            0.7875621521403985
                        ],
                        "val_accuracy": [
                            0.6968806295629089,
                            0.7014582345690717,
                            0.7011737934957808,
                            0.701166208400493,
                            0.7036806674883853,
                            0.7013330804968237,
                            0.7036692898454537,
                            0.7014923674978667,
                            0.7034986252014791,
                            0.7020915900255997
                        ]
                    },
                    "P2": {
                        "loss": [
                            0.21074996957618622,
                            0.12459860344078451,
                            0.10933262783748733,
                            0.10098711850767868,
                            0.0964409342934759,
                            0.09318963327158401,
                            0.09068511054383314,
                            0.08853897300473054,
                            0.08698039912119919,
                            0.08609861577947074
                        ],
                        "accuracy": [
                            0.9316690641368803,
                            0.961861256274392,
                            0.9664194844528609,
                            0.9685385142968129,
                            0.9697106951449711,
                            0.9704860794988984,
                            0.971136279490401,
                            0.9716332234745716,
                            0.972004224403212,
                            0.972218934552098
                        ],
                        "val_loss": [
                            0.13950168641238367,
                            0.11676492253332733,
                            0.1030622228523719,
                            0.09755261021275492,
                            0.09414449668113141,
                            0.09085535365967001,
                            0.08825619693668553,
                            0.08780658239034089,
                            0.08569622866839743,
                            0.08437885577609508
                        ],
                        "val_accuracy": [
                            0.9571328339812268,
                            0.964702759078411,
                            0.9684194557694131,
                            0.9702247084478999,
                            0.9712562814070351,
                            0.9704712240447521,
                            0.9717531051483834,
                            0.9715710628614772,
                            0.9726026358206125,
                            0.9736076609462406
                        ]
                    }
                },
                "global_evaluation": {
                    "P1": {
                        "loss": 1.8071555193858293,
                        "accuracy": 0.6033260642836825
                    },
                    "P2": {
                        "loss": 2.9790221090100664,
                        "accuracy": 0.4735147435289656
                    }
                }
            },
            {
                "round": 3,
                "time": 249.27422785758972,
                "client_training": {
                    "P1": {
                        "loss": [
                            0.8015806013997887,
                            0.7888876240609882,
                            0.7867038588523951,
                            0.7851304340817804,
                            0.7841587079992581,
                            0.7831921315352646,
                            0.7824350852376531,
                            0.7816925673776622,
                            0.7811161795031311,
                            0.7807920168769459
                        ],
                        "accuracy": [
                            0.6988944324065138,
                            0.7015490995830223,
                            0.7020574239637769,
                            0.7024109749509885,
                            0.7029481296697561,
                            0.7034913539333686,
                            0.7036711641993967,
                            0.7038077289584054,
                            0.7040057478589681,
                            0.7039192568449292
                        ],
                        "val_loss": [
                            0.7892720927158622,
                            0.7883703587034183,
                            0.7847106410139848,
                            0.7844154945319102,
                            0.7834774827028074,
                            0.7825703578577614,
                            0.7815122731102466,
                            0.7807112642257736,
                            0.7807200432221585,
                            0.7805150525425467
                        ],
                        "val_accuracy": [
                            0.7015720109983882,
                            0.703817199203565,
                            0.7009348629942164,
                            0.7019436806674884,
                            0.7040295818716222,
                            0.7047539584716033,
                            0.7056527922632028,
                            0.7051028728548402,
                            0.7030055940077747,
                            0.7051749312600739
                        ]
                    },
                    "P2": {
                        "loss": [
                            0.1758934129266813,
                            0.10510755984492402,
                            0.0947021713786877,
                            0.08948989924722035,
                            0.08657605541217325,
                            0.08441029707379463,
                            0.08266201361282945,
                            0.08123584078422466,
                            0.07987967384366432,
                            0.07875751972336321
                        ],
                        "accuracy": [
                            0.9455918413178196,
                            0.9687243941076858,
                            0.9712918115770498,
                            0.9724336447009839,
                            0.9731377119029844,
                            0.9735511996455386,
                            0.97404283277797,
                            0.974316720989093,
                            0.9747233804936968,
                            0.9749449188805331
                        ],
                        "val_loss": [
                            0.1193113317337716,
                            0.09866500551625769,
                            0.09137766930521117,
                            0.08652496935663556,
                            0.08436938784815208,
                            0.0859606843438546,
                            0.08203185229100492,
                            0.08018665472274597,
                            0.07860862774595533,
                            0.07837340324125301
                        ],
                        "val_accuracy": [
                            0.9623627571821372,
                            0.9703308997819285,
                            0.9731108372048923,
                            0.9729287949179861,
                            0.974005878448848,
                            0.9733080496823742,
                            0.9747150848582535,
                            0.9745899307860055,
                            0.9754204987200151,
                            0.9751360576467242
                        ]
                    }
                },
                "global_evaluation": {
                    "P1": {
                        "loss": 1.5391323011385114,
                        "accuracy": 0.6002237603109889
                    },
                    "P2": {
                        "loss": 1.9278720369191602,
                        "accuracy": 0.6080819190291078
                    }
                }
            },
            {
                "round": 4,
                "time": 245.9815149307251,
                "client_training": {
                    "P1": {
                        "loss": [
                            0.7911273966571736,
                            0.784559243397127,
                            0.7831412950456925,
                            0.782497786153016,
                            0.7820644362024166,
                            0.7818548877599828,
                            0.7814606699953701,
                            0.7813160063320236,
                            0.7815242762413147,
                            0.7810337220416966
                        ],
                        "accuracy": [
                            0.7013844631791062,
                            0.7023624185922298,
                            0.7032091200980839,
                            0.7036544729510734,
                            0.7037568965203299,
                            0.703764483451386,
                            0.703885115655177,
                            0.7039222916173516,
                            0.7037751051548644,
                            0.70391394599319
                        ],
                        "val_loss": [
                            0.7856117819200322,
                            0.7840932494223914,
                            0.7811680116065252,
                            0.7827629530259169,
                            0.7807699802001641,
                            0.7802824720430342,
                            0.7796686631312831,
                            0.7822987934927517,
                            0.781037191868597,
                            0.7800798089888307
                        ],
                        "val_accuracy": [
                            0.703877879965867,
                            0.7038702948705793,
                            0.7029790461742675,
                            0.7029790461742675,
                            0.7027932113397175,
                            0.7051559685218546,
                            0.7051559685218546,
                            0.7029866312695553,
                            0.7051711387124301,
                            0.7052507822129516
                        ]
                    },
                    "P2": {
                        "loss": [
                            0.11448843928482258,
                            0.08676517762779308,
                            0.08251390729416493,
                            0.08072365780911293,
                            0.07914099661785193,
                            0.07804940818896099,
                            0.07733195719321084,
                            0.0765042978294631,
                            0.07580509077924306,
                            0.07516954377634287
                        ],
                        "accuracy": [
                            0.9671144473375941,
                            0.972787954381301,
                            0.9738690920567866,
                            0.9743220318408322,
                            0.9748015258835739,
                            0.9752354983399795,
                            0.9752476374296691,
                            0.9756474686963225,
                            0.9758743179348981,
                            0.9761337909770146
                        ],
                        "val_loss": [
                            0.09038116467225672,
                            0.08278203179743139,
                            0.0823578345726155,
                            0.07894186626641889,
                            0.07926037502987324,
                            0.07718204910262134,
                            0.07973615613307639,
                            0.07564475270386069,
                            0.07641017115872269,
                            0.07434450176752969
                        ],
                        "val_accuracy": [
                            0.9725533327012421,
                            0.9739224424006827,
                            0.9734028633734711,
                            0.9753863657912203,
                            0.9757921683891154,
                            0.9758452640561297,
                            0.9741917132833982,
                            0.97640276855978,
                            0.9752801744571916,
                            0.9764634493220821
                        ]
                    }
                },
                "global_evaluation": {
                    "P1": {
                        "loss": 1.608647900170666,
                        "accuracy": 0.6562017635346544
                    },
                    "P2": {
                        "loss": 1.2753577110070442,
                        "accuracy": 0.6665061154830757
                    }
                }
            },
            {
                "round": 5,
                "time": 227.6318290233612,
                "client_training": {
                    "P1": {
                        "loss": [
                            0.7889783182811101,
                            0.7831879402434538,
                            0.7822035727178677,
                            0.7818984597639369,
                            0.7815060201841199,
                            0.7813312964470157,
                            0.7810135420550859,
                            0.7808529329776599,
                            0.780909558390499,
                            0.7805221413889813
                        ],
                        "accuracy": [
                            0.7021446736709214,
                            0.7033130610535516,
                            0.7035801210267242,
                            0.703747033509957,
                            0.7038600787826921,
                            0.7038661483275369,
                            0.7039814696795887,
                            0.7039093938345563,
                            0.7039845044520111,
                            0.7039996783141232
                        ],
                        "val_loss": [
                            0.7831101263644311,
                            0.7816051644307805,
                            0.7819347062761483,
                            0.780721456665693,
                            0.7813778027794627,
                            0.7802992169226562,
                            0.7799562975866846,
                            0.7791307573948266,
                            0.7794872709668801,
                            0.7805056577688644
                        ],
                        "val_accuracy": [
                            0.7026035839575234,
                            0.7029790461742675,
                            0.7028614771973073,
                            0.7027932113397175,
                            0.7051635536171423,
                            0.7049815113302361,
                            0.7051559685218546,
                            0.7051597610694984,
                            0.705614866786764,
                            0.7052280269270883
                        ]
                    },
                    "P2": {
                        "loss": [
                            0.09854227468558881,
                            0.07963856402424509,
                            0.07755786416243372,
                            0.07623507527515534,
                            0.07528115125583501,
                            0.07477306378086014,
                            0.07431194604684842,
                            0.07370734761837854,
                            0.07347891038477129,
                            0.07294839116029839
                        ],
                        "accuracy": [
                            0.9701401154427429,
                            0.9748106302008412,
                            0.9753750978714106,
                            0.975830313734773,
                            0.9761717256322948,
                            0.9763105664706204,
                            0.9764410616847843,
                            0.9766390805853469,
                            0.9766474262095085,
                            0.9768727580618729
                        ],
                        "val_loss": [
                            0.08185997185909863,
                            0.07987378060820544,
                            0.07766552404997597,
                            0.07548109141968998,
                            0.07628371468709409,
                            0.07409808978569771,
                            0.07560069547653356,
                            0.07343883757383504,
                            0.07395203125774097,
                            0.07266242614640232
                        ],
                        "val_accuracy": [
                            0.9746088935242249,
                            0.97482886128757,
                            0.9751550203849436,
                            0.9761979709870106,
                            0.9752801744571916,
                            0.9766454916089884,
                            0.9762965772257514,
                            0.9767630605859486,
                            0.9766189437754812,
                            0.9770512942068835
                        ]
                    }
                },
                "global_evaluation": {
                    "P1": {
                        "loss": 1.7680612471183466,
                        "accuracy": 0.5704484687588888
                    },
                    "P2": {
                        "loss": 1.0357320916730668,
                        "accuracy": 0.71375367403053
                    }
                }
            },
            {
                "round": 6,
                "time": 239.1513957977295,
                "client_training": {
                    "P1": {
                        "loss": [
                            0.7883629655634262,
                            0.7825820665205468,
                            0.7818867392420651,
                            0.7815401239025034,
                            0.781717416264904,
                            0.7815441781141587,
                            0.7813520538389935,
                            0.7811859548947482,
                            0.7809899247316282,
                            0.7808788270063018
                        ],
                        "accuracy": [
                            0.702867708200562,
                            0.7036415751682781,
                            0.7037060640822544,
                            0.7037811746997092,
                            0.7037250314098946,
                            0.7037439987375347,
                            0.7038919438931275,
                            0.7039814696795887,
                            0.704074788931578,
                            0.7041256213696535
                        ],
                        "val_loss": [
                            0.7857220952273704,
                            0.781300369653813,
                            0.7822783051371699,
                            0.7796377485479078,
                            0.7819724879156777,
                            0.7811260301727496,
                            0.7808060995015847,
                            0.7808484868713044,
                            0.7790868459740691,
                            0.7815025663660682
                        ],
                        "val_accuracy": [
                            0.7051711387124301,
                            0.702808381530293,
                            0.7051749312600739,
                            0.7029790461742675,
                            0.7025846212193041,
                            0.7056186593344079,
                            0.704890490186783,
                            0.7049625485920167,
                            0.7053531809993363,
                            0.7034417369868209
                        ]
                    },
                    "P2": {
                        "loss": [
                            0.0899231024756886,
                            0.0760809875032289,
                            0.07461150705517165,
                            0.0733741198431914,
                            0.07274990897916392,
                            0.07239730225028826,
                            0.07184086325696336,
                            0.07160959928863614,
                            0.07140169797838883,
                            0.07104221487331523
                        ],
                        "accuracy": [
                            0.9724086078284989,
                            0.9758690070831588,
                            0.976362916294907,
                            0.9767149498959073,
                            0.9769273839654764,
                            0.9770480161692675,
                            0.9772460350698301,
                            0.9774068780082181,
                            0.977416741018591,
                            0.9774888168636234
                        ],
                        "val_loss": [
                            0.07662442501655199,
                            0.07562106817412559,
                            0.07528351634706922,
                            0.07260701981838748,
                            0.07177027611551301,
                            0.07286017921874113,
                            0.07141876985436313,
                            0.07112354963441432,
                            0.07032202219111418,
                            0.07209035415671794
                        ],
                        "val_accuracy": [
                            0.9763572579880535,
                            0.9760121361524604,
                            0.976501374798521,
                            0.9765734332037547,
                            0.9770057836351569,
                            0.9767440978477292,
                            0.9777074049492747,
                            0.9776050061628899,
                            0.9776429316393287,
                            0.9770209538257324
                        ]
                    }
                },
                "global_evaluation": {
                    "P1": {
                        "loss": 1.7858580731943205,
                        "accuracy": 0.5857627761448754
                    },
                    "P2": {
                        "loss": 0.9212024786949972,
                        "accuracy": 0.7541405138902058
                    }
                }
            },
            {
                "round": 7,
                "time": 231.12197184562683,
                "client_training": {
                    "P1": {
                        "loss": [
                            0.7889390747771897,
                            0.7823516225503261,
                            0.7818486850468348,
                            0.7815870038461236,
                            0.7812796118354837,
                            0.7809511464808925,
                            0.7809207058685399,
                            0.780725893547875,
                            0.7805489333054478,
                            0.7803851066737382
                        ],
                        "accuracy": [
                            0.7023745576819195,
                            0.7034640409815668,
                            0.703622607840638,
                            0.7038327658308904,
                            0.7039549154208926,
                            0.7040687193867332,
                            0.7041939037491578,
                            0.7042417014148109,
                            0.7042477709596557,
                            0.7043365380530114
                        ],
                        "val_loss": [
                            0.7817854900040015,
                            0.7827656525754924,
                            0.7797052317521488,
                            0.7797936848313749,
                            0.7810269220268443,
                            0.7802993127311182,
                            0.7798566529775012,
                            0.7790791216138031,
                            0.778905880246398,
                            0.7801217325099715
                        ],
                        "val_accuracy": [
                            0.7027211529344838,
                            0.70473120318574,
                            0.7025542808381531,
                            0.702713567839196,
                            0.70473120318574,
                            0.7055996965961885,
                            0.7053493884516924,
                            0.7033696785815872,
                            0.7055428083815303,
                            0.7049815113302361
                        ]
                    },
                    "P2": {
                        "loss": [
                            0.08649168048541628,
                            0.07400056206306413,
                            0.0726628397049787,
                            0.07182157318040273,
                            0.0713041430159789,
                            0.07075304148755039,
                            0.07051216597246869,
                            0.07007223573693667,
                            0.06988602665211374,
                            0.06955329078281475
                        ],
                        "accuracy": [
                            0.9732378593929242,
                            0.9765973524645387,
                            0.9769744229380238,
                            0.9772604502388366,
                            0.9774448126634984,
                            0.9776367620192162,
                            0.9776663510503347,
                            0.9778082266610827,
                            0.9778560243267357,
                            0.9779698282925764
                        ],
                        "val_loss": [
                            0.07351674640168508,
                            0.07351426774103449,
                            0.073722475517177,
                            0.07133250143055081,
                            0.071014583621125,
                            0.0707107688874399,
                            0.07066580155921048,
                            0.06993068926694032,
                            0.06903648075435109,
                            0.07068369788050685
                        ],
                        "val_accuracy": [
                            0.9767061723712904,
                            0.9769602730634304,
                            0.9766834170854272,
                            0.9774874371859297,
                            0.9779008248791126,
                            0.977885654688537,
                            0.9778591068550299,
                            0.9777036124016308,
                            0.9774988148288613,
                            0.9778818621408931
                        ]
                    }
                },
                "global_evaluation": {
                    "P1": {
                        "loss": 1.7886653548995046,
                        "accuracy": 0.6560690243671186
                    },
                    "P2": {
                        "loss": 1.5527363018565938,
                        "accuracy": 0.6956366739357163
                    }
                }
            },
            {
                "round": 8,
                "time": 245.34093117713928,
                "client_training": {
                    "P1": {
                        "loss": [
                            0.7891258215424815,
                            0.7818841511461423,
                            0.7810813225764834,
                            0.7803125091385612,
                            0.7794566066171176,
                            0.7785851530619886,
                            0.7777102442861231,
                            0.7767414997729528,
                            0.7757256000462935,
                            0.7747123457728676
                        ],
                        "accuracy": [
                            0.7023912489302427,
                            0.7036696468131854,
                            0.7039109112207675,
                            0.7041468647766104,
                            0.7043395728254338,
                            0.7045512482018973,
                            0.7047204367644471,
                            0.7048494145923997,
                            0.7049556316271843,
                            0.7051642722312254
                        ],
                        "val_loss": [
                            0.781947647112856,
                            0.7811327906725044,
                            0.7791423777011691,
                            0.7818602112111089,
                            0.779408612869764,
                            0.7804222070554812,
                            0.7764364837124029,
                            0.7750380404112835,
                            0.7750432389458627,
                            0.7758136992702284
                        ],
                        "val_accuracy": [
                            0.70473120318574,
                            0.702713567839196,
                            0.7033620934862994,
                            0.7049701336873044,
                            0.7055314307385987,
                            0.7049663411396606,
                            0.7055314307385987,
                            0.7056186593344079,
                            0.7055276381909548,
                            0.705645207167915
                        ]
                    },
                    "P2": {
                        "loss": [
                            0.0901716201884277,
                            0.07253372314560269,
                            0.07139847626848576,
                            0.07076779707379552,
                            0.07010988807193375,
                            0.0697610331871603,
                            0.06943170839563649,
                            0.06927506323972016,
                            0.06889424833721436,
                            0.06875000503965253
                        ],
                        "accuracy": [
                            0.9729730754990683,
                            0.9771732005316921,
                            0.977485782091201,
                            0.9777490485988456,
                            0.9778552656336301,
                            0.9779508609649362,
                            0.9780722518618329,
                            0.978054801920404,
                            0.978164053727611,
                            0.9782626838313395
                        ],
                        "val_loss": [
                            0.07327756567683233,
                            0.07222900015944224,
                            0.07011347825788622,
                            0.07363982468411133,
                            0.07101471138009531,
                            0.06811746426331462,
                            0.07120032447590086,
                            0.06902439024789284,
                            0.06757859876757834,
                            0.06913648700170452
                        ],
                        "val_accuracy": [
                            0.9773660756613255,
                            0.9771499004456243,
                            0.9775329477576562,
                            0.9765089598938087,
                            0.9777794633545084,
                            0.9785872760026548,
                            0.9777567080686451,
                            0.9783938560728169,
                            0.9791523656015929,
                            0.9787996586707121
                        ]
                    }
                },
                "global_evaluation": {
                    "P1": {
                        "loss": 1.6594772942307843,
                        "accuracy": 0.652648146392339
                    },
                    "P2": {
                        "loss": 2.1714959708346995,
                        "accuracy": 0.6577984260927278
                    }
                }
            },
            {
                "round": 9,
                "time": 248.1000587940216,
                "client_training": {
                    "P1": {
                        "loss": [
                            0.7855163599600025,
                            0.7778614100131869,
                            0.77619984902211,
                            0.7753149126555368,
                            0.7748032641783309,
                            0.7742225765578509,
                            0.7738980102034172,
                            0.7736790009405999,
                            0.7734105493291921,
                            0.7732504266462451
                        ],
                        "accuracy": [
                            0.7027804584934175,
                            0.704212871076798,
                            0.7045353156466797,
                            0.7047378867058759,
                            0.7048312059578652,
                            0.7049533555478674,
                            0.705034535710167,
                            0.7051134397931499,
                            0.7051961373416608,
                            0.7052477284728418
                        ],
                        "val_loss": [
                            0.7779321711581273,
                            0.7787803962891436,
                            0.7744325576009847,
                            0.776108571536577,
                            0.773527722927002,
                            0.7747096931038054,
                            0.7735871262960415,
                            0.7735656229683582,
                            0.7746823729062245,
                            0.7738284011410234
                        ],
                        "val_accuracy": [
                            0.704890490186783,
                            0.7049815113302361,
                            0.7048942827344269,
                            0.7054100692139945,
                            0.7049473784014412,
                            0.7048222243291932,
                            0.7054176543092823,
                            0.7045150279700388,
                            0.7046629373281502,
                            0.7054707499762966
                        ]
                    },
                    "P2": {
                        "loss": [
                            0.10772007244428823,
                            0.07684575897770718,
                            0.07377547260805901,
                            0.0720640280674629,
                            0.07104721245680409,
                            0.07023232099260607,
                            0.0698268875792225,
                            0.06941111707574216,
                            0.06909261440273902,
                            0.06874940969834571
                        ],
                        "accuracy": [
                            0.9700999047081459,
                            0.9761595865426052,
                            0.9768666885170281,
                            0.9772376894456685,
                            0.9774774364670393,
                            0.9776322098605825,
                            0.9778264352956172,
                            0.9779978999374837,
                            0.9780381106720807,
                            0.9782103340070528
                        ],
                        "val_loss": [
                            0.08010887241588449,
                            0.07477438652403515,
                            0.07368768031787927,
                            0.0727599071291902,
                            0.06957014709442637,
                            0.07016870421383678,
                            0.06912568887816997,
                            0.06920211345129718,
                            0.06969775948603198,
                            0.06758120887783271
                        ],
                        "val_accuracy": [
                            0.9754546316488101,
                            0.9767137574665782,
                            0.9768009860623874,
                            0.9771347302550488,
                            0.9778325590215227,
                            0.9780373565942923,
                            0.9777984260927278,
                            0.9781359628330331,
                            0.9776770645681236,
                            0.978864131980658
                        ]
                    }
                },
                "global_evaluation": {
                    "P1": {
                        "loss": 1.9373957060031488,
                        "accuracy": 0.5805897411586233
                    },
                    "P2": {
                        "loss": 1.242316737319888,
                        "accuracy": 0.7297923580164976
                    }
                }
            },
            {
                "round": 10,
                "time": 239.97788286209106,
                "client_training": {
                    "P1": {
                        "loss": [
                            0.7893236651878713,
                            0.7764543672058654,
                            0.7752907694149781,
                            0.7747698666076861,
                            0.7741733108739007,
                            0.7737883494602384,
                            0.773541518925884,
                            0.7734541390115487,
                            0.7732748341280207,
                            0.7730602885449986
                        ],
                        "accuracy": [
                            0.7014952323725244,
                            0.7044442724740072,
                            0.7046119436503456,
                            0.7047052629023349,
                            0.7048038930060635,
                            0.7048000995405355,
                            0.704866105840723,
                            0.7048858318614687,
                            0.7049783924203524,
                            0.7050216379273718
                        ],
                        "val_loss": [
                            0.777107879819605,
                            0.7748026891741197,
                            0.7739025240739262,
                            0.7735483368050943,
                            0.773065074083081,
                            0.7752155060454817,
                            0.7743664473217788,
                            0.7727784139931207,
                            0.7740683605454596,
                            0.7726676957996307
                        ],
                        "val_accuracy": [
                            0.7048032615909737,
                            0.7049625485920167,
                            0.7049397933061534,
                            0.7050346069972504,
                            0.7049246231155779,
                            0.7050004740684555,
                            0.7053911064757751,
                            0.7047767137574665,
                            0.7047501659239594,
                            0.7055996965961885
                        ]
                    },
                    "P2": {
                        "loss": [
                            0.09442498660007652,
                            0.07402555547697183,
                            0.07120439049105871,
                            0.07026222200460554,
                            0.06980647335217234,
                            0.06897130007590284,
                            0.06865135445119126,
                            0.06819793410721828,
                            0.06760326222205625,
                            0.0674064012682123
                        ],
                        "accuracy": [
                            0.97139878730494,
                            0.9765685221265258,
                            0.9774266040289639,
                            0.9777869832541257,
                            0.9777376682022615,
                            0.9781170147550635,
                            0.9781777102035119,
                            0.9784387006318396,
                            0.9787459713396093,
                            0.9787414191809756
                        ],
                        "val_loss": [
                            0.07468535128116574,
                            0.07113572229504178,
                            0.0702290587075499,
                            0.06951020604791919,
                            0.06852819079628056,
                            0.0679863136081212,
                            0.06809462509869207,
                            0.06747521559745878,
                            0.06811258451074484,
                            0.06761985217845642
                        ],
                        "val_accuracy": [
                            0.9772029961126386,
                            0.9775632881388072,
                            0.9773926234948327,
                            0.9775329477576562,
                            0.9785265952403527,
                            0.9781170000948137,
                            0.9785493505262159,
                            0.9781321702853892,
                            0.9782269839764862,
                            0.9789020574570968
                        ]
                    }
                },
                "global_evaluation": {
                    "P1": {
                        "loss": 1.9207434226737108,
                        "accuracy": 0.580536645491609
                    },
                    "P2": {
                        "loss": 1.6465613921658173,
                        "accuracy": 0.6666767801270503
                    }
                }
            }
        ],
        "final_evaluation": {
            "P1": {
                "loss": 1.9207434226737108,
                "accuracy": 0.580536645491609
            },
            "P2": {
                "loss": 1.6465613921658173,
                "accuracy": 0.6666767801270503
            }
        }
    }
}