{
    "timestamp": "2025-03-04 20:50:08",
    "config": {
        "experiment_name": "fl_experiment",
        "experiment_type": "suppression",
        "data_path": "datasets/dataset.parquet",
        "p1_path": null,
        "p2_path": null,
        "feature_columns": [
            "protocol",
            "bidirectional_min_ps",
            "bidirectional_mean_ps",
            "bidirectional_stddev_ps",
            "bidirectional_max_ps",
            "src2dst_stddev_ps",
            "src2dst_max_ps",
            "dst2src_min_ps",
            "dst2src_mean_ps",
            "dst2src_stddev_ps",
            "dst2src_max_ps",
            "bidirectional_stddev_piat_ms",
            "bidirectional_max_piat_ms",
            "bidirectional_rst_packets"
        ],
        "target_column": "application_name",
        "seed": 42,
        "initial_split_ratio": 0.5,
        "test_split_ratio": 0.1667,
        "batch_size": 256,
        "learning_rate": 0.001,
        "local_epochs": 100,
        "federated_rounds": 10,
        "client_epochs": 10,
        "p1_features": null,
        "p2_features": null,
        "max_parallel_suppression_processes": 10,
        "noise_multiplier_p1": null,
        "noise_multiplier_p2": null,
        "noise_multiplier_p1_explicitly_set": false,
        "noise_multiplier_p2_explicitly_set": false,
        "max_grad_norm": 1.0,
        "max_epsilon": 10.0,
        "max_parallel_dp_processes": 2,
        "results_dir": "results",
        "logs_dir": "logs",
        "save_models": false,
        "checkpoint_interval": 1
    },
    "results": {
        "experiment_id": "56",
        "p1_features": [
            "protocol",
            "bidirectional_min_ps",
            "bidirectional_mean_ps",
            "bidirectional_stddev_ps",
            "bidirectional_max_ps",
            "src2dst_stddev_ps",
            "src2dst_max_ps",
            "dst2src_min_ps",
            "dst2src_mean_ps",
            "dst2src_stddev_ps",
            "dst2src_max_ps"
        ],
        "p2_features": [
            "protocol"
        ],
        "rounds": [
            {
                "round": 1,
                "time": 230.0257179737091,
                "client_training": {
                    "P1": {
                        "loss": [
                            0.39066358909443294,
                            0.21734029970492846,
                            0.1947194724648087,
                            0.17192776213523933,
                            0.14137743278271828,
                            0.12537736949307732,
                            0.11730966827630457,
                            0.1122515698199361,
                            0.10897163520230811,
                            0.10680408715688788
                        ],
                        "accuracy": [
                            0.8606971175731531,
                            0.9245555575787372,
                            0.9329193903749158,
                            0.9410859629636373,
                            0.9543175707253713,
                            0.9593871580570174,
                            0.9621958399339634,
                            0.9638088214764775,
                            0.964965069769418,
                            0.9657935626407376
                        ],
                        "val_loss": [
                            0.23965949970952274,
                            0.20242687177135898,
                            0.18502263692540447,
                            0.1542435180647538,
                            0.12946322514596703,
                            0.12111911117047215,
                            0.11379676357122172,
                            0.1086065992488334,
                            0.1067633456355126,
                            0.10497234225979549
                        ],
                        "val_accuracy": [
                            0.9113795392054612,
                            0.9289959230112829,
                            0.9353711956006447,
                            0.947920735754243,
                            0.9590139376125912,
                            0.959935526690054,
                            0.9644903764103536,
                            0.9649568597705509,
                            0.9662994216364843,
                            0.9663335545652793
                        ]
                    },
                    "P2": {
                        "loss": [
                            1.3673744154398124,
                            1.3319781561286284,
                            1.3319212328987762,
                            1.3318418308727944,
                            1.3318358531604244,
                            1.3317692908201015,
                            1.3317620663270489,
                            1.3317233779494249,
                            1.3317104395800332,
                            1.3317086238670706
                        ],
                        "accuracy": [
                            0.4823558331360731,
                            0.49285842179694944,
                            0.49285842179694944,
                            0.49285842179694944,
                            0.49285842179694944,
                            0.49285842179694944,
                            0.49285842179694944,
                            0.49285842179694944,
                            0.49285842179694944,
                            0.49285842179694944
                        ],
                        "val_loss": [
                            1.3322663156882477,
                            1.3322897965740546,
                            1.3321449537196746,
                            1.3317518053355912,
                            1.3320226815635925,
                            1.3317600680215897,
                            1.3315226428339444,
                            1.3316239172462672,
                            1.3316692925991465,
                            1.3314984066171918
                        ],
                        "val_accuracy": [
                            0.49285673651275247,
                            0.49285673651275247,
                            0.49285673651275247,
                            0.49285673651275247,
                            0.49285673651275247,
                            0.49285673651275247,
                            0.49285673651275247,
                            0.49285673651275247,
                            0.49285673651275247,
                            0.49285673651275247
                        ]
                    }
                },
                "global_evaluation": {
                    "P1": {
                        "loss": 1.0415195091349192,
                        "accuracy": 0.6125988432729687
                    },
                    "P2": {
                        "loss": 1.7926421005949427,
                        "accuracy": 0.49285673651275247
                    }
                }
            },
            {
                "round": 2,
                "time": 247.316636800766,
                "client_training": {
                    "P1": {
                        "loss": [
                            0.16452503082233727,
                            0.11606796922140775,
                            0.10750347815387847,
                            0.10310121229045517,
                            0.10006976539907879,
                            0.09679684043889301,
                            0.09364870676187707,
                            0.09206820952226062,
                            0.09056541883379,
                            0.08937573844081974
                        ],
                        "accuracy": [
                            0.9503313971485279,
                            0.9628467986185716,
                            0.9657799061648367,
                            0.9671979035792106,
                            0.9683958799929593,
                            0.9697372494036672,
                            0.9707728654928167,
                            0.9711946988595326,
                            0.9716575016539509,
                            0.9719700832134598
                        ],
                        "val_loss": [
                            0.12277072827827538,
                            0.11143511426644358,
                            0.1070128213813647,
                            0.10210503158478236,
                            0.10002912654485184,
                            0.09353412739101084,
                            0.09183593902018122,
                            0.09083432020975016,
                            0.09145001996082865,
                            0.08809634324265982
                        ],
                        "val_accuracy": [
                            0.9613122214847823,
                            0.9641414620271167,
                            0.9655788375841472,
                            0.9670465535223286,
                            0.9685863278657438,
                            0.9703612401630796,
                            0.9716241585284915,
                            0.9712790366928985,
                            0.9716886318384375,
                            0.9725419550583104
                        ]
                    },
                    "P2": {
                        "loss": [
                            1.3341062536842019,
                            1.3324867990375426,
                            1.3323087022770745,
                            1.3321759134433886,
                            1.3320611275096836,
                            1.3319827272079934,
                            1.3319368204093158,
                            1.3318714897152613,
                            1.3318397449486359,
                            1.3317736333797219
                        ],
                        "accuracy": [
                            0.49285842179694944,
                            0.49285842179694944,
                            0.49285842179694944,
                            0.49285842179694944,
                            0.49285842179694944,
                            0.49285842179694944,
                            0.49285842179694944,
                            0.49285842179694944,
                            0.49285842179694944,
                            0.49285842179694944
                        ],
                        "val_loss": [
                            1.3322824882672073,
                            1.3327665623120248,
                            1.3321989770766127,
                            1.3315892688088975,
                            1.331745061664612,
                            1.3318693360525522,
                            1.3319659099179195,
                            1.3317300787412398,
                            1.3317823114347218,
                            1.3317913343461756
                        ],
                        "val_accuracy": [
                            0.49285673651275247,
                            0.49285673651275247,
                            0.49285673651275247,
                            0.49285673651275247,
                            0.49285673651275247,
                            0.49285673651275247,
                            0.49285673651275247,
                            0.49285673651275247,
                            0.49285673651275247,
                            0.49285673651275247
                        ]
                    }
                },
                "global_evaluation": {
                    "P1": {
                        "loss": 0.5640272073822812,
                        "accuracy": 0.8133801080876079
                    },
                    "P2": {
                        "loss": 1.814032617222475,
                        "accuracy": 0.3957788944723618
                    }
                }
            },
            {
                "round": 3,
                "time": 239.71681714057922,
                "client_training": {
                    "P1": {
                        "loss": [
                            0.11521061008660805,
                            0.0958346396611071,
                            0.09198786484536878,
                            0.09003493831425281,
                            0.08881730646114058,
                            0.08767962186780283,
                            0.08684643040061481,
                            0.08603561505605403,
                            0.08537407929918675,
                            0.08473813926058014
                        ],
                        "accuracy": [
                            0.9645212343026397,
                            0.9699307161455962,
                            0.9712614638528256,
                            0.9716999884678648,
                            0.972149893479488,
                            0.9725262052598675,
                            0.9727204306949022,
                            0.972985214588758,
                            0.9731225380408723,
                            0.9732704831964651
                        ],
                        "val_loss": [
                            0.09828506498381663,
                            0.09407798450575447,
                            0.09059895320798567,
                            0.08847307337495154,
                            0.09095430119835371,
                            0.08861419537736645,
                            0.08677687866305801,
                            0.08597391786694673,
                            0.08464731445431291,
                            0.08346853156657516
                        ],
                        "val_accuracy": [
                            0.969875794064663,
                            0.9693941405138902,
                            0.9712790366928985,
                            0.9725381625106665,
                            0.9718024082677539,
                            0.9727164122499289,
                            0.9732246136342088,
                            0.9729287949179861,
                            0.9739982933535603,
                            0.9738200436142979
                        ]
                    },
                    "P2": {
                        "loss": [
                            1.3343983024719257,
                            1.3326276046422274,
                            1.3325527241609192,
                            1.3324049547018624,
                            1.332367274658847,
                            1.3322008847003692,
                            1.3320773458402981,
                            1.3319834425527268,
                            1.3318813753350036,
                            1.3318152430726704
                        ],
                        "accuracy": [
                            0.4926588855101756,
                            0.49285842179694944,
                            0.49285842179694944,
                            0.49285842179694944,
                            0.49285842179694944,
                            0.49285842179694944,
                            0.49285842179694944,
                            0.49285842179694944,
                            0.49285842179694944,
                            0.49285842179694944
                        ],
                        "val_loss": [
                            1.332161279631597,
                            1.3329441856675615,
                            1.3321028781138382,
                            1.3333299656561723,
                            1.3328031410569205,
                            1.3320759036831011,
                            1.3325267146663824,
                            1.3319622081474658,
                            1.3316980121725033,
                            1.3317419813413287
                        ],
                        "val_accuracy": [
                            0.49285673651275247,
                            0.49285673651275247,
                            0.49285673651275247,
                            0.49285673651275247,
                            0.49285673651275247,
                            0.49285673651275247,
                            0.49285673651275247,
                            0.49285673651275247,
                            0.49285673651275247,
                            0.49285673651275247
                        ]
                    }
                },
                "global_evaluation": {
                    "P1": {
                        "loss": 0.8381539993726033,
                        "accuracy": 0.8019455769413103
                    },
                    "P2": {
                        "loss": 1.8403048715006405,
                        "accuracy": 0.3957788944723618
                    }
                }
            },
            {
                "round": 4,
                "time": 209.9638340473175,
                "client_training": {
                    "P1": {
                        "loss": [
                            0.10361384863296888,
                            0.08894238026607852,
                            0.08694374146582218,
                            0.08569556978427528,
                            0.08453600211973025,
                            0.08397285813999318,
                            0.0833646344034744,
                            0.08283748768974433,
                            0.08218727852363156,
                            0.08175586590903433
                        ],
                        "accuracy": [
                            0.9690521495293068,
                            0.9721711368864449,
                            0.9726483548498698,
                            0.9729920428267084,
                            0.9733675959139824,
                            0.9735565104972778,
                            0.9736763840079632,
                            0.9737924640531207,
                            0.9739730330122545,
                            0.9741133912367912
                        ],
                        "val_loss": [
                            0.09015326978994273,
                            0.08819690448495578,
                            0.08595229834126016,
                            0.08654208433976204,
                            0.08353893207844777,
                            0.08353383531669446,
                            0.08532029088808031,
                            0.08155614785900203,
                            0.08316512382015229,
                            0.0824636932894993
                        ],
                        "val_accuracy": [
                            0.9716279510761354,
                            0.9727619228216554,
                            0.973152555228975,
                            0.9728415663221769,
                            0.973342182611169,
                            0.9735280174457192,
                            0.972333364937897,
                            0.9742106760216175,
                            0.9742675642362757,
                            0.9736986820896938
                        ]
                    },
                    "P2": {
                        "loss": [
                            1.3346900412259215,
                            1.332718359817493,
                            1.3325835440431288,
                            1.3324474077601787,
                            1.3323440254836187,
                            1.3321653353407998,
                            1.332111896597678,
                            1.3320157215257595,
                            1.3319578722277698,
                            1.3318891762627862
                        ],
                        "accuracy": [
                            0.4927355135138416,
                            0.49285842179694944,
                            0.49285842179694944,
                            0.49285842179694944,
                            0.49285842179694944,
                            0.49285842179694944,
                            0.49285842179694944,
                            0.49285842179694944,
                            0.49285842179694944,
                            0.49285842179694944
                        ],
                        "val_loss": [
                            1.332161038748583,
                            1.3328076381110079,
                            1.3325588798875592,
                            1.332909435705968,
                            1.3318458983266797,
                            1.3320744994024174,
                            1.3315745934497873,
                            1.3315890577681044,
                            1.3317436554398685,
                            1.332166520479766
                        ],
                        "val_accuracy": [
                            0.49285673651275247,
                            0.49285673651275247,
                            0.49285673651275247,
                            0.49285673651275247,
                            0.49285673651275247,
                            0.49285673651275247,
                            0.49285673651275247,
                            0.49285673651275247,
                            0.49285673651275247,
                            0.49285673651275247
                        ]
                    }
                },
                "global_evaluation": {
                    "P1": {
                        "loss": 0.9138190032362746,
                        "accuracy": 0.7757504503650328
                    },
                    "P2": {
                        "loss": 1.7595761796672433,
                        "accuracy": 0.3957788944723618
                    }
                }
            },
            {
                "round": 5,
                "time": 231.84366488456726,
                "client_training": {
                    "P1": {
                        "loss": [
                            0.09494509075604358,
                            0.08469910838800966,
                            0.083339227924272,
                            0.08237460009603613,
                            0.08184261139166907,
                            0.08105059481034242,
                            0.08060166744425455,
                            0.07996274107626684,
                            0.07959681618655613,
                            0.07901780188642679
                        ],
                        "accuracy": [
                            0.9712720855563042,
                            0.9732856570585772,
                            0.9736414841251054,
                            0.9738630225119418,
                            0.9740048981226898,
                            0.9742067104887805,
                            0.974309134058037,
                            0.9745382593759294,
                            0.9747066892453735,
                            0.974834149687115
                        ],
                        "val_loss": [
                            0.08621589282010646,
                            0.08320312787263079,
                            0.08138505758304579,
                            0.0823326436660861,
                            0.08051511494929366,
                            0.08014666674687443,
                            0.08127805458682176,
                            0.07883050551882251,
                            0.07864855414601009,
                            0.07735929149693874
                        ],
                        "val_accuracy": [
                            0.9723826680572675,
                            0.9734180335640467,
                            0.9741196548781644,
                            0.9738883094718878,
                            0.9748174836446383,
                            0.9749691855503935,
                            0.9738958945671755,
                            0.974889542049872,
                            0.9749160898833792,
                            0.9751550203849436
                        ]
                    },
                    "P2": {
                        "loss": [
                            1.3344972769083627,
                            1.3327354501673492,
                            1.3325554647329738,
                            1.332466431935391,
                            1.3322976077376478,
                            1.3322347424691436,
                            1.3321411311707834,
                            1.3320758211339707,
                            1.3319952285866359,
                            1.3319195207035581
                        ],
                        "accuracy": [
                            0.4927795177139666,
                            0.49285842179694944,
                            0.49285842179694944,
                            0.49285842179694944,
                            0.49285842179694944,
                            0.49285842179694944,
                            0.49285842179694944,
                            0.49285842179694944,
                            0.49285842179694944,
                            0.49285842179694944
                        ],
                        "val_loss": [
                            1.3338732166657394,
                            1.3322424776999207,
                            1.3324706045096324,
                            1.3321909585048364,
                            1.3319191383264342,
                            1.3317851387336603,
                            1.331832153857958,
                            1.3317134942006554,
                            1.3319171076389673,
                            1.3323123186970816
                        ],
                        "val_accuracy": [
                            0.49285673651275247,
                            0.49285673651275247,
                            0.49285673651275247,
                            0.49285673651275247,
                            0.49285673651275247,
                            0.49285673651275247,
                            0.49285673651275247,
                            0.49285673651275247,
                            0.49285673651275247,
                            0.49285673651275247
                        ]
                    }
                },
                "global_evaluation": {
                    "P1": {
                        "loss": 1.0782506355233834,
                        "accuracy": 0.7119711766379065
                    },
                    "P2": {
                        "loss": 1.8287664835389965,
                        "accuracy": 0.33604247653361147
                    }
                }
            },
            {
                "round": 6,
                "time": 242.09999680519104,
                "client_training": {
                    "P1": {
                        "loss": [
                            0.09017394251414498,
                            0.0819037758435321,
                            0.08055259059856339,
                            0.07977543496717358,
                            0.07915400730228771,
                            0.07869435211233608,
                            0.07817588776154302,
                            0.07782579042216932,
                            0.07732682497865719,
                            0.07693314400991022
                        ],
                        "accuracy": [
                            0.972059608999921,
                            0.9740443501641812,
                            0.9743007884338754,
                            0.9745375006828237,
                            0.9747150348695351,
                            0.9748333909940093,
                            0.9750056143289815,
                            0.9751656985742639,
                            0.975290124243583,
                            0.9754858670648288
                        ],
                        "val_loss": [
                            0.08317004341067347,
                            0.080935452632416,
                            0.08005739447654475,
                            0.08087868094585558,
                            0.07749572817065585,
                            0.07773900001882275,
                            0.07910776308707584,
                            0.07774976048306671,
                            0.08242890446615228,
                            0.07610100859743821
                        ],
                        "val_accuracy": [
                            0.972997060775576,
                            0.9742144685692614,
                            0.9748781644069404,
                            0.9745140798331279,
                            0.9752460415283967,
                            0.9756897696027307,
                            0.9752270787901773,
                            0.974855409121077,
                            0.9743510002844411,
                            0.9761600455105717
                        ]
                    },
                    "P2": {
                        "loss": [
                            1.334940498707451,
                            1.3328709735886395,
                            1.332643171606228,
                            1.3325791622108716,
                            1.3324281327438237,
                            1.332260483587888,
                            1.3321934086665048,
                            1.3321350876931348,
                            1.3320650956870013,
                            1.332004816682763
                        ],
                        "accuracy": [
                            0.4928318675382533,
                            0.49285842179694944,
                            0.49285842179694944,
                            0.49285842179694944,
                            0.49285842179694944,
                            0.49285842179694944,
                            0.49285842179694944,
                            0.49285842179694944,
                            0.49285842179694944,
                            0.49285842179694944
                        ],
                        "val_loss": [
                            1.333622958407624,
                            1.332431824757294,
                            1.3328687198509974,
                            1.3321747924158718,
                            1.3320960105741557,
                            1.332502091785647,
                            1.331771544343636,
                            1.3317157423366266,
                            1.3315518359576424,
                            1.3320184360224567
                        ],
                        "val_accuracy": [
                            0.49285673651275247,
                            0.49285673651275247,
                            0.49285673651275247,
                            0.49285673651275247,
                            0.49285673651275247,
                            0.49285673651275247,
                            0.49285673651275247,
                            0.49285673651275247,
                            0.49285673651275247,
                            0.49285673651275247
                        ]
                    }
                },
                "global_evaluation": {
                    "P1": {
                        "loss": 1.12836683428795,
                        "accuracy": 0.6996795297240922
                    },
                    "P2": {
                        "loss": 1.8541893691380036,
                        "accuracy": 0.33604247653361147
                    }
                }
            },
            {
                "round": 7,
                "time": 245.64728999137878,
                "client_training": {
                    "P1": {
                        "loss": [
                            0.0878144956829121,
                            0.07900984588116061,
                            0.07792875887282917,
                            0.07715884174897011,
                            0.07644425639519724,
                            0.0760121432516945,
                            0.07545584672399187,
                            0.07511032024303017,
                            0.0748562331949985,
                            0.07442729399837784
                        ],
                        "accuracy": [
                            0.9727674696674496,
                            0.9748743604217119,
                            0.9751710094260031,
                            0.9754608301923439,
                            0.9756891968171307,
                            0.9758401767451459,
                            0.9759979849111116,
                            0.9761444126804931,
                            0.9761307562045922,
                            0.9763871944742863
                        ],
                        "val_loss": [
                            0.0780990622353755,
                            0.07894152061274304,
                            0.07798509069049178,
                            0.07598163250483721,
                            0.0780280046857702,
                            0.07598769682980075,
                            0.07655681766622596,
                            0.0740403888124566,
                            0.07387077407809166,
                            0.0733254645900036
                        ],
                        "val_accuracy": [
                            0.9754242912676591,
                            0.9747037072153218,
                            0.9751967384090262,
                            0.9761638380582156,
                            0.9749426377168863,
                            0.9761903858917228,
                            0.9754204987200151,
                            0.9766075661325495,
                            0.9757049397933062,
                            0.9761676306058595
                        ]
                    },
                    "P2": {
                        "loss": [
                            1.334738027993973,
                            1.3328309143211892,
                            1.3326781153649228,
                            1.3325963122995903,
                            1.3324247299541336,
                            1.3323336328997046,
                            1.3322841211945144,
                            1.3321539540072236,
                            1.3320132648225578,
                            1.3320086486300917
                        ],
                        "accuracy": [
                            0.4926444703411691,
                            0.49285842179694944,
                            0.49285842179694944,
                            0.49285842179694944,
                            0.49285842179694944,
                            0.49285842179694944,
                            0.49285842179694944,
                            0.49285842179694944,
                            0.49285842179694944,
                            0.49285842179694944
                        ],
                        "val_loss": [
                            1.3322602804027892,
                            1.3339609787983386,
                            1.3318050149570566,
                            1.3320090382126504,
                            1.332392198408544,
                            1.3319762998672982,
                            1.3316051640080606,
                            1.331612794291886,
                            1.3316366819617895,
                            1.3316577012317152
                        ],
                        "val_accuracy": [
                            0.49285673651275247,
                            0.49285673651275247,
                            0.49285673651275247,
                            0.49285673651275247,
                            0.49285673651275247,
                            0.49285673651275247,
                            0.49285673651275247,
                            0.49285673651275247,
                            0.49285673651275247,
                            0.49285673651275247
                        ]
                    }
                },
                "global_evaluation": {
                    "P1": {
                        "loss": 1.0919120764472399,
                        "accuracy": 0.7074656300369774
                    },
                    "P2": {
                        "loss": 1.9018991793041784,
                        "accuracy": 0.33604247653361147
                    }
                }
            },
            {
                "round": 8,
                "time": 245.44628405570984,
                "client_training": {
                    "P1": {
                        "loss": [
                            0.08534463591225122,
                            0.07683948817633597,
                            0.07585481698974494,
                            0.07534456826526506,
                            0.07468436427580245,
                            0.07444801600944742,
                            0.07402328917934296,
                            0.07381096832943548,
                            0.07359117365530563,
                            0.07320344801777036
                        ],
                        "accuracy": [
                            0.973699903494237,
                            0.9757036119861372,
                            0.9759168047488119,
                            0.9761239279666418,
                            0.9763568467500622,
                            0.9763765727708079,
                            0.9764668572503747,
                            0.9765032745194437,
                            0.9766201132577068,
                            0.9766838434785775
                        ],
                        "val_loss": [
                            0.07589262499793555,
                            0.07420792050506364,
                            0.07412558253029065,
                            0.07429820053660159,
                            0.07338711471556543,
                            0.07343414674566641,
                            0.0733742948330397,
                            0.07479746350404141,
                            0.0720114248666626,
                            0.07249144706152068
                        ],
                        "val_accuracy": [
                            0.9760159287001043,
                            0.976307954868683,
                            0.9761448753199962,
                            0.9765734332037547,
                            0.9767896084194557,
                            0.975833886413198,
                            0.9763458803451218,
                            0.9766416990613445,
                            0.9768540817294017,
                            0.9764710344173698
                        ]
                    },
                    "P2": {
                        "loss": [
                            1.3349378969050318,
                            1.3327699521229894,
                            1.3326936169022645,
                            1.3324717526736645,
                            1.332350014060034,
                            1.3323046688047835,
                            1.3322366843446742,
                            1.3321943265527825,
                            1.3321132619682945,
                            1.3320728037454677
                        ],
                        "accuracy": [
                            0.4926065356858889,
                            0.49285842179694944,
                            0.49285842179694944,
                            0.49285842179694944,
                            0.49285842179694944,
                            0.49285842179694944,
                            0.49285842179694944,
                            0.49285842179694944,
                            0.49285842179694944,
                            0.49285842179694944
                        ],
                        "val_loss": [
                            1.3318961690439028,
                            1.3326255449887485,
                            1.3329518299721266,
                            1.3319921777426287,
                            1.3328860891262049,
                            1.33202152496335,
                            1.3339838519502818,
                            1.3322466190634175,
                            1.331701153544687,
                            1.332039409454167
                        ],
                        "val_accuracy": [
                            0.49285673651275247,
                            0.49285673651275247,
                            0.49285673651275247,
                            0.49285673651275247,
                            0.49285673651275247,
                            0.49285673651275247,
                            0.49285673651275247,
                            0.49285673651275247,
                            0.49285673651275247,
                            0.49285673651275247
                        ]
                    }
                },
                "global_evaluation": {
                    "P1": {
                        "loss": 1.0506597443984178,
                        "accuracy": 0.7192794159476629
                    },
                    "P2": {
                        "loss": 1.9094378822815297,
                        "accuracy": 0.33604247653361147
                    }
                }
            },
            {
                "round": 9,
                "time": 232.24644494056702,
                "client_training": {
                    "P1": {
                        "loss": [
                            0.08331638277566446,
                            0.0752284042254351,
                            0.07434986598418286,
                            0.07373985109172135,
                            0.07330779567315837,
                            0.07295757695514556,
                            0.0726234912572495,
                            0.07242431851475839,
                            0.072113884040152,
                            0.07185649735600524
                        ],
                        "accuracy": [
                            0.9741536019713881,
                            0.9761891755737238,
                            0.9764524420813683,
                            0.9766572892198814,
                            0.9767225368269633,
                            0.9767915778995733,
                            0.976960766462123,
                            0.9769455926000109,
                            0.9771428528074679,
                            0.9772612089319422
                        ],
                        "val_loss": [
                            0.07428333049095942,
                            0.07524536386529247,
                            0.0729402386358341,
                            0.0750217747595894,
                            0.07173372277597392,
                            0.07241149902185512,
                            0.07275135592059907,
                            0.07111047532903568,
                            0.07342032607084961,
                            0.07341996839033876
                        ],
                        "val_accuracy": [
                            0.9763951834644923,
                            0.9759021522707879,
                            0.9766416990613445,
                            0.9766341139660567,
                            0.9765658481084669,
                            0.9762738219398881,
                            0.9764862046079454,
                            0.9766910021807149,
                            0.9755228975064,
                            0.9774077936854082
                        ]
                    },
                    "P2": {
                        "loss": [
                            1.3351470318176997,
                            1.332790032807959,
                            1.3326249552500091,
                            1.332466243272185,
                            1.3324294289101473,
                            1.3323467546424566,
                            1.332252309273402,
                            1.3322103103697964,
                            1.3321375507432833,
                            1.3320383954528736
                        ],
                        "accuracy": [
                            0.4926444703411691,
                            0.49285842179694944,
                            0.49285842179694944,
                            0.49285842179694944,
                            0.49285842179694944,
                            0.49285842179694944,
                            0.49285842179694944,
                            0.49285842179694944,
                            0.49285842179694944,
                            0.49285842179694944
                        ],
                        "val_loss": [
                            1.3331655894128747,
                            1.3322149197325341,
                            1.3332509564259294,
                            1.335508972523596,
                            1.3317717849743742,
                            1.3319939281292366,
                            1.332152687321684,
                            1.3320426351497148,
                            1.3323288747269,
                            1.3319124625804493
                        ],
                        "val_accuracy": [
                            0.49285673651275247,
                            0.49285673651275247,
                            0.49285673651275247,
                            0.49285673651275247,
                            0.49285673651275247,
                            0.49285673651275247,
                            0.49285673651275247,
                            0.49285673651275247,
                            0.49285673651275247,
                            0.49285673651275247
                        ]
                    }
                },
                "global_evaluation": {
                    "P1": {
                        "loss": 0.9776876338796162,
                        "accuracy": 0.746657817388831
                    },
                    "P2": {
                        "loss": 1.9556878090384018,
                        "accuracy": 0.33604247653361147
                    }
                }
            },
            {
                "round": 10,
                "time": 243.19458508491516,
                "client_training": {
                    "P1": {
                        "loss": [
                            0.08093711045142327,
                            0.07374414743921924,
                            0.0729491392643064,
                            0.07264688796163422,
                            0.07227743988377336,
                            0.07187157708014205,
                            0.07168261632118411,
                            0.07135078996517405,
                            0.07116397322089754,
                            0.07100341707163962
                        ],
                        "accuracy": [
                            0.9746687545900933,
                            0.9766990173406896,
                            0.9768196495444806,
                            0.9769417991344829,
                            0.9770480161692675,
                            0.9772012721765995,
                            0.9772847284182159,
                            0.9773431477873474,
                            0.9774319148807031,
                            0.9775798600362959
                        ],
                        "val_loss": [
                            0.07222705811510789,
                            0.07189296234628313,
                            0.07129743759391872,
                            0.07326145215860484,
                            0.07035043520630226,
                            0.07235899410982928,
                            0.07097639512349455,
                            0.07004547568666288,
                            0.06959846260407032,
                            0.06889383787481584
                        ],
                        "val_accuracy": [
                            0.9771081824215416,
                            0.9775594955911634,
                            0.9770057836351569,
                            0.9767023798236465,
                            0.9779577130937708,
                            0.9774570968047787,
                            0.9770209538257324,
                            0.9777453304257134,
                            0.9780487342372238,
                            0.9782876647387883
                        ]
                    },
                    "P2": {
                        "loss": [
                            1.335194794715514,
                            1.332776303418144,
                            1.3326332280405702,
                            1.3325286411638966,
                            1.3324196959087133,
                            1.3323002042241734,
                            1.3321961146212182,
                            1.3321693222746036,
                            1.3321537905284875,
                            1.3320816568359422
                        ],
                        "accuracy": [
                            0.4926042596065721,
                            0.49285842179694944,
                            0.49285842179694944,
                            0.49285842179694944,
                            0.49285842179694944,
                            0.49285842179694944,
                            0.49285842179694944,
                            0.49285842179694944,
                            0.49285842179694944,
                            0.49285842179694944
                        ],
                        "val_loss": [
                            1.3323410705549408,
                            1.3317134332751803,
                            1.3322903825276675,
                            1.3319106192397565,
                            1.3321302503308403,
                            1.333210618850167,
                            1.331770569966892,
                            1.3317598448363008,
                            1.3323731861356831,
                            1.332083514334184
                        ],
                        "val_accuracy": [
                            0.49285673651275247,
                            0.49285673651275247,
                            0.49285673651275247,
                            0.49285673651275247,
                            0.49285673651275247,
                            0.49285673651275247,
                            0.49285673651275247,
                            0.49285673651275247,
                            0.49285673651275247,
                            0.49285673651275247
                        ]
                    }
                },
                "global_evaluation": {
                    "P1": {
                        "loss": 1.03618684067685,
                        "accuracy": 0.7273234095003318
                    },
                    "P2": {
                        "loss": 1.9852408802650592,
                        "accuracy": 0.3957788944723618
                    }
                }
            }
        ],
        "final_evaluation": {
            "P1": {
                "loss": 1.03618684067685,
                "accuracy": 0.7273234095003318
            },
            "P2": {
                "loss": 1.9852408802650592,
                "accuracy": 0.3957788944723618
            }
        }
    }
}